LICENSE.txt
README.md
setup.py
tsd/__about__.py
tsd/__init__.py
tsd/extract_mgrs_tile_coordinates_from_kml.py
tsd/get_landsat.py
tsd/get_planet.py
tsd/get_sentinel1.py
tsd/get_sentinel2.py
tsd/get_sentinel3.py
tsd/l8_metadata_parser.py
tsd/parallel.py
tsd/s1_metadata_parser.py
tsd/s2_metadata_parser.py
tsd/s3_metadata_parser.py
tsd/search_airbus.py
tsd/search_gcloud.py
tsd/search_mundi.py
tsd/search_planet.py
tsd/search_scihub.py
tsd/search_stac.py
tsd/test_search_scihub.py
tsd/test_search_stac.py
tsd/utils.py
tsd.egg-info/PKG-INFO
tsd.egg-info/SOURCES.txt
tsd.egg-info/dependency_links.txt
tsd.egg-info/requires.txt
tsd.egg-info/top_level.txt