Metadata-Version: 2.1
Name: tsd
Version: 0.9.0
Summary: Search and download of Sentinel, Landsat and Planet crops.
Home-page: https://github.com/centreborelli/tsd
Author: Carlo de Franchis
Author-email: carlo.de-franchis@ens-paris-saclay.fr
License: UNKNOWN
Platform: UNKNOWN
Requires-Python: >=3.5
Provides-Extra: gcp
Provides-Extra: planet
Provides-Extra: sentinelhub
License-File: LICENSE.txt
